MANIFEST.in
README.md
setup.py
src/alba_client/__init__.py
src/alba_client/callback.py
src/alba_client/client.py
src/alba_client/exceptions.py
src/alba_client/recurrent.py
src/alba_client/service.py
src/alba_client/sign.py
src/alba_client/tests.py
src/alba_client_python.egg-info/PKG-INFO
src/alba_client_python.egg-info/SOURCES.txt
src/alba_client_python.egg-info/dependency_links.txt
src/alba_client_python.egg-info/requires.txt
src/alba_client_python.egg-info/top_level.txt