Metadata-Version: 1.1
Name: alba-client-python
Version: 1.0.9
Summary: API client for Alba.
Home-page: https://github.com/RFIBANK/alba-client-python
Author: UNKNOWN
Author-email: UNKNOWN
License: GPL v3
Platform: UNKNOWN
Classifier: Intended Audience :: Developers
Classifier: License :: OSI Approved :: GNU Lesser General Public License v3 or later (LGPLv3+)
Classifier: Operating System :: OS Independent
Classifier: Programming Language :: Python
Classifier: Topic :: Internet :: WWW/HTTP
